cs3/__init__.py
cs3/admin/__init__.py
cs3/admin/group/__init__.py
cs3/admin/group/v1beta1/__init__.py
cs3/admin/group/v1beta1/group_api_pb2.py
cs3/admin/group/v1beta1/group_api_pb2_grpc.py
cs3/admin/user/__init__.py
cs3/admin/user/v1beta1/__init__.py
cs3/admin/user/v1beta1/user_api_pb2.py
cs3/admin/user/v1beta1/user_api_pb2_grpc.py
cs3/app/__init__.py
cs3/app/provider/__init__.py
cs3/app/provider/v1beta1/__init__.py
cs3/app/provider/v1beta1/provider_api_pb2.py
cs3/app/provider/v1beta1/provider_api_pb2_grpc.py
cs3/app/provider/v1beta1/resources_pb2.py
cs3/app/provider/v1beta1/resources_pb2_grpc.py
cs3/app/registry/__init__.py
cs3/app/registry/v1beta1/__init__.py
cs3/app/registry/v1beta1/registry_api_pb2.py
cs3/app/registry/v1beta1/registry_api_pb2_grpc.py
cs3/app/registry/v1beta1/resources_pb2.py
cs3/app/registry/v1beta1/resources_pb2_grpc.py
cs3/auth/__init__.py
cs3/auth/applications/__init__.py
cs3/auth/applications/v1beta1/__init__.py
cs3/auth/applications/v1beta1/applications_api_pb2.py
cs3/auth/applications/v1beta1/applications_api_pb2_grpc.py
cs3/auth/applications/v1beta1/resources_pb2.py
cs3/auth/applications/v1beta1/resources_pb2_grpc.py
cs3/auth/provider/__init__.py
cs3/auth/provider/v1beta1/__init__.py
cs3/auth/provider/v1beta1/provider_api_pb2.py
cs3/auth/provider/v1beta1/provider_api_pb2_grpc.py
cs3/auth/provider/v1beta1/resources_pb2.py
cs3/auth/provider/v1beta1/resources_pb2_grpc.py
cs3/auth/registry/__init__.py
cs3/auth/registry/v1beta1/__init__.py
cs3/auth/registry/v1beta1/registry_api_pb2.py
cs3/auth/registry/v1beta1/registry_api_pb2_grpc.py
cs3/auth/registry/v1beta1/resources_pb2.py
cs3/auth/registry/v1beta1/resources_pb2_grpc.py
cs3/gateway/__init__.py
cs3/gateway/v1beta1/__init__.py
cs3/gateway/v1beta1/gateway_api_pb2.py
cs3/gateway/v1beta1/gateway_api_pb2_grpc.py
cs3/gateway/v1beta1/resources_pb2.py
cs3/gateway/v1beta1/resources_pb2_grpc.py
cs3/identity/__init__.py
cs3/identity/group/__init__.py
cs3/identity/group/v1beta1/__init__.py
cs3apis-0.2.20260130.3789864.dist-info/licenses/LICENSE
cs3apis-0.2.20260130.3789864.dist-info/METADATA
cs3apis-0.2.20260130.3789864.dist-info/WHEEL
cs3apis-0.2.20260130.3789864.dist-info/top_level.txt
cs3apis-0.2.20260130.3789864.dist-info/RECORD
