Metadata-Version: 2.4
Name: cs3apis
Version: 0.2.20260130.3789864
Summary: CS3 API bindings for Python
Home-page: https://github.com/cs3org/python-cs3apis
Author: CS3 Organization
Author-email: contact@cs3community.org
Classifier: Programming Language :: Python :: 3
Classifier: License :: OSI Approved :: Apache Software License
Classifier: Operating System :: OS Independent
Requires-Python: >=3.6
License-File: LICENSE
Dynamic: author
Dynamic: author-email
Dynamic: classifier
Dynamic: description
Dynamic: description-content-type
Dynamic: home-page
Dynamic: license-file
Dynamic: requires-python
Dynamic: summary
